setup.py
algomize/__init__.py
algomize/pso.py
algomize.egg-info/PKG-INFO
algomize.egg-info/SOURCES.txt
algomize.egg-info/dependency_links.txt
algomize.egg-info/top_level.txt