Metadata-Version: 1.0
Name: algomize
Version: 0.1.0
Summary: Optimizers for sklearn
Home-page: UNKNOWN
Author: Muyide Ibukun
Author-email: UNKNOWN
License: UNKNOWN
Platform: UNKNOWN
